ssutils/__init__.py
ssutils/datelib.py
ssutils/echo.py
ssutils/sfdc.py
ssutils-0.4.7.dist-info/LICENSE
ssutils-0.4.7.dist-info/METADATA
ssutils-0.4.7.dist-info/WHEEL
ssutils-0.4.7.dist-info/top_level.txt
ssutils-0.4.7.dist-info/RECORD
