Metadata-Version: 2.1
Name: ssutils
Version: 0.4.7
Summary: collection of useful python functions
Home-page: https://github.com/satapathy/pypi-ssutils
Author: S Satapathy
Author-email: shubhakant.satapathy@gmail.com
License: UNKNOWN
Platform: UNKNOWN
Classifier: Programming Language :: Python :: 3
Classifier: License :: OSI Approved :: MIT License
Classifier: Operating System :: OS Independent
Requires-Dist: simple-salesforce
